Metadata-Version: 1.1
Name: secrets-manager
Version: 0.4
Summary: Managing access to secrets.
Home-page: https://github.com/CuriBio/secrets-manager
Author: Curi Bio
Author-email: contact@curibio.com
License: MIT
Platform: UNKNOWN
Classifier: Development Status :: 1 - Planning
Classifier: Intended Audience :: Science/Research
Classifier: License :: OSI Approved :: MIT License
Classifier: Programming Language :: Python
Classifier: Programming Language :: Python :: 3
Classifier: Programming Language :: Python :: 3.7
Classifier: Programming Language :: Python :: 3.8
Classifier: Topic :: Security
